README.md
setup.py
document_polluter/__init__.py
document_polluter/pollution.yaml
document_polluter/tests.py
document_polluter.egg-info/PKG-INFO
document_polluter.egg-info/SOURCES.txt
document_polluter.egg-info/dependency_links.txt
document_polluter.egg-info/requires.txt
document_polluter.egg-info/top_level.txt