Metadata-Version: 2.1
Name: document-polluter
Version: 0.0.7
Summary: Pollutes documents with terms biased on specific geners
Home-page: https://github.com/gregology/document-polluter
Author: Greg Clarke
Author-email: greg@gho.st
License: MIT
Keywords: stop words machine learning ml bias biased natural language processing nlp
Platform: UNKNOWN
Classifier: Development Status :: 4 - Beta
Classifier: Intended Audience :: Developers
Classifier: Topic :: Software Development :: Build Tools
Classifier: License :: OSI Approved :: MIT License
Classifier: Programming Language :: Python
